setup.py
xooof/__init__.py
xooof.xmldispatcher.egg-info/PKG-INFO
xooof.xmldispatcher.egg-info/SOURCES.txt
xooof.xmldispatcher.egg-info/dependency_links.txt
xooof.xmldispatcher.egg-info/entry_points.txt
xooof.xmldispatcher.egg-info/namespace_packages.txt
xooof.xmldispatcher.egg-info/not-zip-safe
xooof.xmldispatcher.egg-info/requires.txt
xooof.xmldispatcher.egg-info/top_level.txt
xooof/xmldispatcher/__init__.py
xooof/xmldispatcher/classinfo/MClass.py
xooof/xmldispatcher/classinfo/MClassMethod.py
xooof/xmldispatcher/classinfo/MInstanceMethod.py
xooof/xmldispatcher/classinfo/MLabel.py
xooof/xmldispatcher/classinfo/MState.py
xooof/xmldispatcher/classinfo/__init__.py
xooof/xmldispatcher/clients/XMLDispatcherClient.py
xooof/xmldispatcher/clients/__init__.py
xooof/xmldispatcher/clients/adapters/__init__.py
xooof/xmldispatcher/clients/adapters/com.py
xooof/xmldispatcher/clients/adapters/dcom.py
xooof/xmldispatcher/clients/adapters/httpform.py
xooof/xmldispatcher/clients/adapters/javaxdclient.py
xooof/xmldispatcher/clients/adapters/soap.py
xooof/xmldispatcher/interfaces/__init__.py
xooof/xmldispatcher/interfaces/interfaces.py
xooof/xmldispatcher/servers/__init__.py
xooof/xmldispatcher/servers/interfaces.py
xooof/xmldispatcher/servers/adapters/__init__.py
xooof/xmldispatcher/servers/adapters/httpform_mod_python.py
xooof/xmldispatcher/servers/adapters/httpform_python.py
xooof/xmldispatcher/servers/adapters/soap_mod_python.py
xooof/xmldispatcher/servers/basic/__init__.py
xooof/xmldispatcher/servers/basic/ctxmgr.py
xooof/xmldispatcher/servers/basic/xdhandlers.py
xooof/xmldispatcher/servers/basic/xdserver.py
xooof/xmldispatcher/servers/tools/__init__.py
xooof/xmldispatcher/servers/tools/boutils.py
xooof/xmldispatcher/servers/tools/fsm.py
xooof/xmldispatcher/servers/tools/metaclass.py
xooof/xmldispatcher/servers/tools/roles.py
xooof/xmldispatcher/tools/__init__.py
xooof/xmldispatcher/tools/envelope/__init__.py
xooof/xmldispatcher/tools/envelope/constants.py
xooof/xmldispatcher/tools/marshallers/ErrorMarshaller.py
xooof/xmldispatcher/tools/marshallers/IXMLDispatcherMarshaller.py
xooof/xmldispatcher/tools/marshallers/StructMarshaller.py
xooof/xmldispatcher/tools/marshallers/__init__.py
xooof/xmldispatcher/tools/unittest/TestCaseBase.py
xooof/xmldispatcher/tools/unittest/TestRunner.py
xooof/xmldispatcher/tools/unittest/__init__.py
